invenio_userprofiles/__init__.py
invenio_userprofiles/api.py
invenio_userprofiles/config.py
invenio_userprofiles/ext.py
invenio_userprofiles/forms.py
invenio_userprofiles/models.py
invenio_userprofiles/validators.py
invenio_userprofiles/views.py
invenio_userprofiles/alembic/41157f1933d6_remove_table.py
invenio_userprofiles/alembic/71634726ec7e_create_userprofiles_branch.py
invenio_userprofiles/alembic/c25ef2c50ffa_create_userprofiles_tables.py
invenio_userprofiles/templates/invenio_userprofiles/base.html
invenio_userprofiles/templates/invenio_userprofiles/register_user.html
invenio_userprofiles/templates/invenio_userprofiles/settings/_macros.html
invenio_userprofiles/templates/invenio_userprofiles/settings/base.html
invenio_userprofiles/templates/invenio_userprofiles/settings/profile.html
invenio_userprofiles/templates/semantic-ui/invenio_userprofiles/base.html
invenio_userprofiles/templates/semantic-ui/invenio_userprofiles/register_user.html
invenio_userprofiles/templates/semantic-ui/invenio_userprofiles/settings/_macros.html
invenio_userprofiles/templates/semantic-ui/invenio_userprofiles/settings/base.html
invenio_userprofiles/templates/semantic-ui/invenio_userprofiles/settings/profile.html
invenio_userprofiles/translations/messages.pot
invenio_userprofiles/translations/ar/LC_MESSAGES/messages.mo
invenio_userprofiles/translations/ar/LC_MESSAGES/messages.po
invenio_userprofiles/translations/bg/LC_MESSAGES/messages.mo
invenio_userprofiles/translations/bg/LC_MESSAGES/messages.po
invenio_userprofiles/translations/ca/LC_MESSAGES/messages.mo
invenio_userprofiles/translations/ca/LC_MESSAGES/messages.po
invenio_userprofiles/translations/cs/LC_MESSAGES/messages.mo
invenio_userprofiles/translations/cs/LC_MESSAGES/messages.po
invenio_userprofiles/translations/da/LC_MESSAGES/messages.mo
invenio_userprofiles/translations/da/LC_MESSAGES/messages.po
invenio_userprofiles/translations/de/LC_MESSAGES/messages.mo
invenio_userprofiles/translations/de/LC_MESSAGES/messages.po
invenio_userprofiles-4.1.1.dist-info/licenses/AUTHORS.rst
invenio_userprofiles-4.1.1.dist-info/licenses/LICENSE
invenio_userprofiles-4.1.1.dist-info/METADATA
invenio_userprofiles-4.1.1.dist-info/WHEEL
invenio_userprofiles-4.1.1.dist-info/entry_points.txt
invenio_userprofiles-4.1.1.dist-info/top_level.txt
invenio_userprofiles-4.1.1.dist-info/RECORD
